setup.py
clustering/__init__.py
otisnguyenclustering2024.egg-info/PKG-INFO
otisnguyenclustering2024.egg-info/SOURCES.txt
otisnguyenclustering2024.egg-info/dependency_links.txt
otisnguyenclustering2024.egg-info/top_level.txt