Metadata-Version: 2.1
Name: otisnguyenclustering2024
Version: 0.0.1
Summary: A modules for data segmentation process
Home-page: 
Author: Otis Nguyen
Author-email: otisnguyen149@gmail.com
License: MIT
Keywords: clustering
Classifier: Development Status :: 5 - Production/Stable
Classifier: Intended Audience :: Education
Classifier: Operating System :: Microsoft :: Windows :: Windows 10
Classifier: License :: OSI Approved :: MIT License
Classifier: Programming Language :: Python :: 3
